tool_aws/__init__.py
tool_aws/utils.py
tool_aws/s3/__init__.py
tool_aws/s3/rm.py
tool_aws/s3/utils.py
tool_aws-0.2.6.dist-info/LICENSE
tool_aws-0.2.6.dist-info/METADATA
tool_aws-0.2.6.dist-info/WHEEL
tool_aws-0.2.6.dist-info/entry_points.txt
tool_aws-0.2.6.dist-info/top_level.txt
tool_aws-0.2.6.dist-info/RECORD
