Metadata-Version: 2.1
Name: tool-aws
Version: 0.2.6
Summary: AWS scripts for geoadmin
Home-page: https://github.com/geoadmin/tool-aws.git
Author: Andrea Borghi, Loic Gasser
Author-email: andrea.borghi@swisstopo.ch, loicgasser4@gmail.com
License: BSD-2
Platform: UNKNOWN
Classifier: Development Status :: 5 - Production/Stable
Classifier: Intended Audience :: Developers
Classifier: License :: OSI Approved :: MIT License
Classifier: Operating System :: OS Independent
Classifier: Programming Language :: Python :: 3.6
Classifier: Programming Language :: Python :: 3.7
Classifier: Programming Language :: Python :: 3.8
Classifier: Programming Language :: Python :: 3.9
Classifier: Topic :: Scientific/Engineering :: GIS
Classifier: Topic :: Software Development :: Libraries :: Python Modules
Requires-Python: >=3.6, <4
Requires-Dist: boto3
Requires-Dist: configparser (>=5.3)
Requires-Dist: gatilegrid (==0.2.0)
Requires-Dist: pyproj (>=3.3)
